toscinterface/__init__.py
toscinterface/oscinterface.py
toscinterface-0.0.2.dist-info/LICENSE
toscinterface-0.0.2.dist-info/METADATA
toscinterface-0.0.2.dist-info/WHEEL
toscinterface-0.0.2.dist-info/top_level.txt
toscinterface-0.0.2.dist-info/RECORD
