Metadata-Version: 2.1
Name: toscinterface
Version: 0.0.2
Summary: A simple package to receive OSC messages sent by TouchOSC
Home-page: UNKNOWN
Author: Marius Seiter
Author-email: mariuss98@hotmail.de
License: MIT
Platform: UNKNOWN
Requires-Python: >=3.10
License-File: LICENSE
